README.md
setup.py
dateparse/__init__.py
dateparse/dateparse.py
dateparse_tobiasli.egg-info/PKG-INFO
dateparse_tobiasli.egg-info/SOURCES.txt
dateparse_tobiasli.egg-info/dependency_links.txt
dateparse_tobiasli.egg-info/requires.txt
dateparse_tobiasli.egg-info/top_level.txt