Metadata-Version: 2.1
Name: dateparse-tobiasli
Version: 1.0.2
Summary: Package for converting string timestamps into datetimes.
Home-page: https://github.com/tobiasli/dateparse
Author: Tobias Litherland
Author-email: tobiaslland@gmail.com
License: UNKNOWN
Platform: UNKNOWN
Classifier: Programming Language :: Python :: 3
Classifier: License :: OSI Approved :: MIT License
Classifier: Operating System :: OS Independent
